{
	"info": {
		"_postman_id": "ed61faef-be5e-4ad7-aee6-f49bf68bb77b",
		"name": "item-local",
		"schema": "https://schema.getpostman.com/json/collection/v2.1.0/collection.json"
	},
	"item": [
		{
			"name": "getuser",
			"request": {
				"method": "GET",
				"header": [],
				"url": {
					"raw": "http://localhost:9000/getuser.php?user=pascal",
					"protocol": "http",
					"host": [
						"localhost"
					],
					"port": "9000",
					"path": [
						"getuser.php"
					],
					"query": [
						{
							"key": "user",
							"value": "pascal"
						}
					]
				},
				"description": "test"
			},
			"response": []
		},
		{
			"name": "getuser isalive",
			"request": {
				"method": "GET",
				"header": [],
				"url": {
					"raw": "http://localhost:9000/getuser.php?isalive=true",
					"protocol": "http",
					"host": [
						"localhost"
					],
					"port": "9000",
					"path": [
						"getuser.php"
					],
					"query": [
						{
							"key": "isalive",
							"value": "true"
						}
					]
				},
				"description": "test"
			},
			"response": []
		},
		{
			"name": "getiem-local",
			"request": {
				"method": "GET",
				"header": [],
				"url": {
					"raw": "http://localhost:9000/getitem.php?key=D51981B6-32B0-4678-95DC-AB1D922C52DC&token=B038D9EB-3ABB-4E9D-B19C-FB973451C7D0",
					"protocol": "http",
					"host": [
						"localhost"
					],
					"port": "9000",
					"path": [
						"getitem.php"
					],
					"query": [
						{
							"key": "key",
							"value": "D51981B6-32B0-4678-95DC-AB1D922C52DC"
						},
						{
							"key": "token",
							"value": "B038D9EB-3ABB-4E9D-B19C-FB973451C7D0"
						}
					]
				},
				"description": "test"
			},
			"response": []
		},
		{
			"name": "getoken",
			"request": {
				"method": "GET",
				"header": [],
				"url": {
					"raw": "http://localhost:9000/getoken.php?key=D51981B6-32B0-4678-95DC-AB1D922C52DC&user=pascal",
					"protocol": "http",
					"host": [
						"localhost"
					],
					"port": "9000",
					"path": [
						"getoken.php"
					],
					"query": [
						{
							"key": "key",
							"value": "D51981B6-32B0-4678-95DC-AB1D922C52DC"
						},
						{
							"key": "user",
							"value": "pascal"
						}
					]
				},
				"description": "test"
			},
			"response": []
		},
		{
			"name": "getiem Copy",
			"request": {
				"method": "GET",
				"header": [],
				"url": {
					"raw": "http://localhost:9000/getitem.php?key=34030B3E-195D-42AA-A827-6C770F42BD06&token=3C5832D-7BCB-46DC-B8CA-169D51BA0D28",
					"protocol": "http",
					"host": [
						"localhost"
					],
					"port": "9000",
					"path": [
						"getitem.php"
					],
					"query": [
						{
							"key": "key",
							"value": "34030B3E-195D-42AA-A827-6C770F42BD06"
						},
						{
							"key": "token",
							"value": "3C5832D-7BCB-46DC-B8CA-169D51BA0D28"
						}
					]
				},
				"description": "test"
			},
			"response": []
		},
		{
			"name": "postuser-local",
			"request": {
				"method": "POST",
				"header": [
					{
						"key": "Content-Type",
						"name": "Content-Type",
						"type": "text",
						"value": "application/x-www-form-urlencoded"
					}
				],
				"body": {
					"mode": "urlencoded",
					"urlencoded": [
						{
							"key": "key",
							"value": "noel",
							"type": "text"
						},
						{
							"key": "user",
							"value": "xxx",
							"type": "text"
						}
					]
				},
				"url": {
					"raw": "http://localhost:9000/postuser.php",
					"protocol": "http",
					"host": [
						"localhost"
					],
					"port": "9000",
					"path": [
						"postuser.php"
					]
				}
			},
			"response": []
		},
		{
			"name": "postitem value + user",
			"request": {
				"method": "POST",
				"header": [
					{
						"key": "Content-Type",
						"name": "Content-Type",
						"value": "application/x-www-form-urlencoded",
						"type": "text"
					}
				],
				"body": {
					"mode": "urlencoded",
					"urlencoded": [
						{
							"key": "key",
							"value": "4265AC3D-DD4B-427C-8BFD-6D7E7BB92C09",
							"type": "text"
						},
						{
							"key": "token",
							"value": "1AA27FFB-1939-4E07-BABC-136A23C42631",
							"type": "text"
						},
						{
							"key": "value",
							"value": "[\n  {\n    \"group\": \"2019-2020\",\n    \"date\": \"2020-01-29T00:00:00.000Z\",\n    \"description\": \"MEC GM Yasser Seirawan\",\n    \"type\": \"Training\"\n  },\n  {\n    \"group\": \"2019-2020\",\n    \"date\": \"2020-01-09T00:00:00.000Z\",\n    \"description\": \"PK Openingsstudie – David van Kerkhof\",\n    \"type\": \"Training\"\n  },\n  {\n    \"group\": \"2019-2020\",\n    \"date\": \"2019-11-04T00:00:00.000Z\",\n    \"description\": \"Ger\",\n    \"type\": \"Training\"\n  },\n  {\n    \"group\": \"2019-2020\",\n    \"date\": \"2019-11-07T00:00:00.000Z\",\n    \"description\": \"John\",\n    \"type\": \"Training\"\n  },\n  {\n    \"group\": \"2019-2020\",\n    \"date\": \"2019-11-15T00:00:00.000Z\",\n    \"description\": \"Hot-Spirit\",\n    \"type\": \"Toernooi\"\n  },\n  {\n    \"group\": \"2019-2020\",\n    \"date\": \"2019-11-20T00:00:00.000Z\",\n    \"description\": \"MEC Jan Timman\",\n    \"type\": \"Training\"\n  },\n  {\n    \"group\": \"2019-2020\",\n    \"date\": \"2019-11-23T00:00:00.000Z\",\n    \"description\": \"Lekstroom 2 - OZU\",\n    \"type\": \"Wedstrijd\"\n  },\n  {\n    \"group\": \"2019-2020\",\n    \"date\": \"2019-12-02T00:00:00.000Z\",\n    \"description\": \"Ger\",\n    \"type\": \"Training\"\n  },\n  {\n    \"group\": \"2019-2020\",\n    \"date\": \"2019-12-12T00:00:00.000Z\",\n    \"description\": \"John\",\n    \"type\": \"Training\"\n  },\n  {\n    \"group\": \"2019-2020\",\n    \"date\": \"2019-12-14T00:00:00.000Z\",\n    \"description\": \"OZU-Almere 4\",\n    \"type\": \"Wedstrijd\"\n  },\n  {\n    \"group\": \"2019-2020\",\n    \"date\": \"2019-12-20T00:00:00.000Z\",\n    \"description\": \"Hot-Spirit\",\n    \"type\": \"Toernooi\"\n  },\n  {\n    \"group\": \"2019-2020\",\n    \"date\": \"2019-12-25T00:00:00.000Z\",\n    \"description\": \"2512 toernooi\",\n    \"type\": \"Toernooi\"\n  },\n  {\n    \"group\": \"2019-2020\",\n    \"date\": \"2020-01-17T00:00:00.000Z\",\n    \"description\": \"Hot-Spirit\",\n    \"type\": \"Toernooi\"\n  },\n  {\n    \"group\": \"2019-2020\",\n    \"date\": \"2020-01-23T00:00:00.000Z\",\n    \"description\": \"John\",\n    \"type\": \"Training\"\n  },\n  {\n    \"group\": \"2019-2020\",\n    \"date\": \"2020-01-24T00:00:00.000Z\",\n    \"description\": \"Wijk aan zee\",\n    \"type\": \"Training\"\n  },\n  {\n    \"group\": \"2019-2020\",\n    \"date\": \"2020-01-25T00:00:00.000Z\",\n    \"description\": \"Wijk aan zee\",\n    \"type\": \"Training\"\n  },\n  {\n    \"group\": \"2019-2020\",\n    \"date\": \"2020-02-01T00:00:00.000Z\",\n    \"description\": \"En Passant 3 - OZU\",\n    \"type\": \"Wedstrijd\"\n  },\n  {\n    \"group\": \"2019-2020\",\n    \"date\": \"2020-02-03T00:00:00.000Z\",\n    \"description\": \"Ger\",\n    \"type\": \"Training\"\n  },\n  {\n    \"group\": \"2019-2020\",\n    \"date\": \"2020-02-20T00:00:00.000Z\",\n    \"description\": \"John\",\n    \"type\": \"Training\"\n  },\n  {\n    \"group\": \"2019-2020\",\n    \"date\": \"2020-02-21T00:00:00.000Z\",\n    \"description\": \"Hot-Spirit\",\n    \"type\": \"Toernooi\"\n  },\n  {\n    \"group\": \"2019-2020\",\n    \"date\": \"2020-03-02T00:00:00.000Z\",\n    \"description\": \"Ger\",\n    \"type\": \"Training\"\n  },\n  {\n    \"group\": \"2019-2020\",\n    \"date\": \"2020-03-07T00:00:00.000Z\",\n    \"description\": \"OZU-ASV 6\",\n    \"type\": \"Wedstrijd\"\n  },\n  {\n    \"group\": \"2019-2020\",\n    \"date\": \"2020-03-20T00:00:00.000Z\",\n    \"description\": \"Hot-Spirit\",\n    \"type\": \"Toernooi\"\n  },\n  {\n    \"group\": \"2019-2020\",\n    \"date\": \"2020-03-28T00:00:00.000Z\",\n    \"description\": \"Magnus 2 - OZU\",\n    \"type\": \"Wedstrijd\"\n  },\n  {\n    \"group\": \"2019-2020\",\n    \"date\": \"2020-04-06T00:00:00.000Z\",\n    \"description\": \"Ger\",\n    \"type\": \"Training\"\n  },\n  {\n    \"group\": \"2019-2020\",\n    \"date\": \"2020-04-16T00:00:00.000Z\",\n    \"description\": \"John\",\n    \"type\": \"Training\"\n  },\n  {\n    \"group\": \"2019-2020\",\n    \"date\": \"2020-04-17T00:00:00.000Z\",\n    \"description\": \"Hot-Spirit\",\n    \"type\": \"Toernooi\"\n  },\n  {\n    \"group\": \"2019-2020\",\n    \"date\": \"2020-04-18T00:00:00.000Z\",\n    \"description\": \"OZU-Wageningen 4\",\n    \"type\": \"Wedstrijd\"\n  },\n  {\n    \"group\": \"2019-2020\",\n    \"date\": \"2020-05-15T00:00:00.000Z\",\n    \"description\": \"Hot-Spirit\",\n    \"type\": \"Toernooi\"\n  },\n  {\n    \"group\": \"2019-2020\",\n    \"date\": \"2020-06-05T00:00:00.000Z\",\n    \"description\": \"OKU\",\n    \"type\": \"Toernooi\"\n  },\n  {\n    \"group\": \"2019-2020\",\n    \"date\": \"2020-06-06T00:00:00.000Z\",\n    \"description\": \"OKU\",\n    \"type\": \"Toernooi\"\n  },\n  {\n    \"group\": \"2019-2020\",\n    \"date\": \"2020-06-07T00:00:00.000Z\",\n    \"description\": \"OKU\",\n    \"type\": \"Toernooi\"\n  },\n  {\n    \"group\": \"2019-2020\",\n    \"date\": \"2020-06-19T00:00:00.000Z\",\n    \"description\": \"Hot-Spirit\",\n    \"type\": \"Toernooi\"\n  }\n]",
							"type": "text"
						}
					],
					"options": {
						"raw": {
							"language": "json"
						}
					}
				},
				"url": {
					"raw": "http://localhost:9000/postitem.php",
					"protocol": "http",
					"host": [
						"localhost"
					],
					"port": "9000",
					"path": [
						"postitem.php"
					]
				}
			},
			"response": []
		},
		{
			"name": "postitem-local with key and token Copy",
			"request": {
				"method": "POST",
				"header": [
					{
						"key": "Content-Type",
						"name": "Content-Type",
						"type": "text",
						"value": "application/x-www-form-urlencoded"
					}
				],
				"body": {
					"mode": "urlencoded",
					"urlencoded": [
						{
							"key": "value",
							"value": "[{\"group\":\"2019-2020\",\"date\":\"2019-11-04T00:00:00.000Z\",\"description\":\"Ger\",\"type\":\"Training\"},{\"group\":\"2019-2020\",\"date\":\"2019-11-07T00:00:00.000Z\",\"description\":\"John\",\"type\":\"Training\"},{\"group\":\"2019-2020\",\"date\":\"2019-11-15T00:00:00.000Z\",\"description\":\"Hot-Spirit\",\"type\":\"Toernooi\"},{\"group\":\"2019-2020\",\"date\":\"2019-11-20T00:00:00.000Z\",\"description\":\"MEC Jan Timman\",\"type\":\"Training\"},{\"group\":\"2019-2020\",\"date\":\"2019-11-23T00:00:00.000Z\",\"description\":\"Lekstroom 2 - OZU\",\"type\":\"Wedstrijd\"},{\"group\":\"2019-2020\",\"date\":\"2019-12-02T00:00:00.000Z\",\"description\":\"Ger\",\"type\":\"Training\"},{\"group\":\"2019-2020\",\"date\":\"2019-12-12T00:00:00.000Z\",\"description\":\"John\",\"type\":\"Training\"},{\"group\":\"2019-2020\",\"date\":\"2019-12-14T00:00:00.000Z\",\"description\":\"OZU-Almere 4\",\"type\":\"Wedstrijd\"},{\"group\":\"2019-2020\",\"date\":\"2019-12-20T00:00:00.000Z\",\"description\":\"Hot-Spirit\",\"type\":\"Toernooi\"},{\"group\":\"2019-2020\",\"date\":\"2019-12-25T00:00:00.000Z\",\"description\":\"2512 toernooi\",\"type\":\"Toernooi\"},{\"group\":\"2019-2020\",\"date\":\"2020-01-17T00:00:00.000Z\",\"description\":\"Hot-Spirit\",\"type\":\"Toernooi\"},{\"group\":\"2019-2020\",\"date\":\"2020-01-23T00:00:00.000Z\",\"description\":\"John\",\"type\":\"Training\"},{\"group\":\"2019-2020\",\"date\":\"2020-01-24T00:00:00.000Z\",\"description\":\"Wijk aan zee\",\"type\":\"Training\"},{\"group\":\"2019-2020\",\"date\":\"2020-01-25T00:00:00.000Z\",\"description\":\"Wijk aan zee\",\"type\":\"Training\"},{\"group\":\"2019-2020\",\"date\":\"2020-02-01T00:00:00.000Z\",\"description\":\"En Passant 3 - OZU\",\"type\":\"Wedstrijd\"},{\"group\":\"2019-2020\",\"date\":\"2020-02-03T00:00:00.000Z\",\"description\":\"Ger\",\"type\":\"Training\"},{\"group\":\"2019-2020\",\"date\":\"2020-02-20T00:00:00.000Z\",\"description\":\"John\",\"type\":\"Training\"},{\"group\":\"2019-2020\",\"date\":\"2020-02-21T00:00:00.000Z\",\"description\":\"Hot-Spirit\",\"type\":\"Toernooi\"},{\"group\":\"2019-2020\",\"date\":\"2020-03-02T00:00:00.000Z\",\"description\":\"Ger\",\"type\":\"Training\"},{\"group\":\"2019-2020\",\"date\":\"2020-03-07T00:00:00.000Z\",\"description\":\"OZU-ASV 6\",\"type\":\"Wedstrijd\"},{\"group\":\"2019-2020\",\"date\":\"2020-03-20T00:00:00.000Z\",\"description\":\"Hot-Spirit\",\"type\":\"Toernooi\"},{\"group\":\"2019-2020\",\"date\":\"2020-03-28T00:00:00.000Z\",\"description\":\"Magnus 2 - OZU\",\"type\":\"Wedstrijd\"},{\"group\":\"2019-2020\",\"date\":\"2020-04-06T00:00:00.000Z\",\"description\":\"Ger\",\"type\":\"Training\"},{\"group\":\"2019-2020\",\"date\":\"2020-04-16T00:00:00.000Z\",\"description\":\"John\",\"type\":\"Training\"},{\"group\":\"2019-2020\",\"date\":\"2020-04-17T00:00:00.000Z\",\"description\":\"Hot-Spirit\",\"type\":\"Toernooi\"},{\"group\":\"2019-2020\",\"date\":\"2020-04-18T00:00:00.000Z\",\"description\":\"OZU-Wageningen 4\",\"type\":\"Wedstrijd\"},{\"group\":\"2019-2020\",\"date\":\"2020-05-15T00:00:00.000Z\",\"description\":\"Hot-Spirit\",\"type\":\"Toernooi\"},{\"group\":\"2019-2020\",\"date\":\"2020-06-05T00:00:00.000Z\",\"description\":\"OKU\",\"type\":\"Toernooi\"},{\"group\":\"2019-2020\",\"date\":\"2020-06-06T00:00:00.000Z\",\"description\":\"OKU\",\"type\":\"Toernooi\"},{\"group\":\"2019-2020\",\"date\":\"2020-06-07T00:00:00.000Z\",\"description\":\"OKU\",\"type\":\"Toernooi\"},{\"group\":\"2019-2020\",\"date\":\"2020-06-19T00:00:00.000Z\",\"description\":\"Hot-Spirit\",\"type\":\"Toernooi\"}]",
							"type": "text"
						},
						{
							"key": "key",
							"value": "D51981B6-32B0-4678-95DC-AB1D922C52DC",
							"type": "text"
						},
						{
							"key": "token",
							"value": "B038D9EB-3ABB-4E9D-B19C-FB973451C7D0",
							"type": "text"
						}
					]
				},
				"url": {
					"raw": "http://localhost:9000/postitem.php",
					"protocol": "http",
					"host": [
						"localhost"
					],
					"port": "9000",
					"path": [
						"postitem.php"
					]
				}
			},
			"response": []
		}
	],
	"protocolProfileBehavior": {}
}